pyDocuProcess.py
pyDocuProcess-0.0.2.dist-info/LICENSE.txt
pyDocuProcess-0.0.2.dist-info/METADATA
pyDocuProcess-0.0.2.dist-info/WHEEL
pyDocuProcess-0.0.2.dist-info/top_level.txt
pyDocuProcess-0.0.2.dist-info/RECORD
